nesdoc/__init__.py
nesdoc/components.py
nesdoc/generators.py
nesdoc/graph.py
nesdoc/html.py
nesdoc/index.py
nesdoc/interfaces.py
nesdoc/utils.py
tinyos3/__init__.py
tinyos3/elf.py
tinyos3/tos.py
tinyos3/tosdevicesearch.py
tinyos3/message/Message.py
tinyos3/message/MoteIF.py
tinyos3/message/SerialPacket.py
tinyos3/message/__init__.py
tinyos3/misc/__init__.py
tinyos3/misc/hexdump.py
tinyos3/packet/IO.py
tinyos3/packet/PacketDispatcher.py
tinyos3/packet/PacketSource.py
tinyos3/packet/Platform.py
tinyos3/packet/SFProtocol.py
tinyos3/packet/SFSource.py
tinyos3/packet/Serial.py
tinyos3/packet/SerialIO.py
tinyos3/packet/SerialProtocol.py
tinyos3/packet/SerialSource.py
tinyos3/packet/SocketIO.py
tinyos3/packet/ThreadTask.py
tinyos3/packet/__init__.py
tinyos3/packet/avrmote.py
tinyos3/tossim/TossimApp.py
tinyos3/tossim/TossimNescDecls.py
tinyos3/tossim/__init__.py
tinyos3/utils/Singleton.py
tinyos3/utils/Watcher.py
tinyos3/utils/__init__.py
tinyos3-2.1.2.3.dist-info/METADATA
tinyos3-2.1.2.3.dist-info/WHEEL
tinyos3-2.1.2.3.dist-info/top_level.txt
tinyos3-2.1.2.3.dist-info/RECORD
